MANIFEST.in
README.rst
setup.py
django_perm.egg-info/PKG-INFO
django_perm.egg-info/SOURCES.txt
django_perm.egg-info/dependency_links.txt
django_perm.egg-info/top_level.txt
perm/__init__.py
perm/apps.py
perm/backends.py
perm/decorators.py
perm/exceptions.py
perm/models.py
perm/permissions.py
perm/shortcuts.py
perm/tests.py
perm/urls.py
perm/utils.py
perm/views.py
perm/templatetags/__init__.py
perm/templatetags/perm.py