Metadata-Version: 1.1
Name: django-perm
Version: 2.4.1
Summary: Class based Django permissions for Django models.
Home-page: https://github.com/dyve/django-perm
Author: Dylan Verheul
Author-email: dylan@dyve.net
License: Apache License 2.0
Platform: UNKNOWN
Classifier: Development Status :: 4 - Beta
Classifier: Intended Audience :: Developers
Classifier: License :: OSI Approved :: Apache Software License
Classifier: Programming Language :: Python
Classifier: Operating System :: OS Independent
Classifier: Topic :: Software Development :: Libraries
Classifier: Topic :: Utilities
Classifier: Environment :: Web Environment
Classifier: Framework :: Django
